AUTHORS
ChangeLog
LICENSE
MANIFEST.in
README.rst
setup.cfg
setup.py
leonardo_sitestarter/__init__.py
leonardo_sitestarter/middleware.py
leonardo_sitestarter/scaffold_web.py
leonardo_sitestarter.egg-info/PKG-INFO
leonardo_sitestarter.egg-info/SOURCES.txt
leonardo_sitestarter.egg-info/dependency_links.txt
leonardo_sitestarter.egg-info/not-zip-safe
leonardo_sitestarter.egg-info/pbr.json
leonardo_sitestarter.egg-info/top_level.txt
leonardo_sitestarter/management/__init__.py
leonardo_sitestarter/management/commands/__init__.py
leonardo_sitestarter/management/commands/bootstrap_site.py